edkrule/__init__.py
edkrule/edk_rule.py
edkrule/engine/__init__.py
edkrule/engine/constant.py
edkrule/engine/engine.py
edkrule/engine/engine_definition.py
edkrule/engine/result.py
edkrule/engine/runner.py
edkrule/engine/finder/__init__.py
edkrule/engine/finder/by.py
edkrule/engine/finder/finder.py
edkrule/engine/finder/finder_by_rid.py
edkrule/engine/finder/finder_by_rule_fragment.py
edkrule/engine/sys/__init__.py
edkrule/engine/sys/engine.xml
edkrule/engine/sys/sys_path.py
edkrule/engine/sys/runner/__init__.py
edkrule/engine/sys/runner/data_type/__init__.py
edkrule/engine/sys/runner/data_type/boolean.py
edkrule/engine/sys/runner/data_type/real_numer.py
edkrule/engine/sys/runner/data_type/variable.py
edkrule/engine/sys/runner/expression/__init__.py
edkrule/engine/sys/runner/expression/and.py
edkrule/engine/sys/runner/expression/auto_increase.py
edkrule/engine/sys/runner/expression/divide.py
edkrule/engine/sys/runner/expression/equal.py
edkrule/engine/sys/runner/expression/greate_than.py
edkrule/engine/sys/runner/expression/less_than.py
edkrule/engine/sys/runner/expression/minus.py
edkrule/engine/sys/runner/expression/multiply.py
edkrule/engine/sys/runner/expression/not_equal.py
edkrule/engine/sys/runner/expression/or.py
edkrule/engine/sys/runner/expression/plus.py
edkrule/engine/sys/runner/expression/todate.py
edkrule/engine/sys/runner/identifier/__init__.py
edkrule/engine/sys/runner/identifier/string.py
edkrule/engine/xml/__init__.py
edkrule/engine/xml/xml_loader.py
edkrule/engine/xml/schema/rule-define.xsd
edkrule/interpreter/__init__.py
edkrule/interpreter/expression/__init__.py
edkrule/interpreter/expression/bracket.py
edkrule/interpreter/expression/bracket_enum.py
edkrule/interpreter/expression/categorize.py
edkrule/interpreter/expression/expression.py
edkrule/interpreter/expression/interpreter.py
edkrule/interpreter/expression/priority.py
edkrule/interpreter/expression/stack.py
edkrule/interpreter/lexer/__init__.py
edkrule/interpreter/lexer/character.py
edkrule-1.0.0.7.dist-info/METADATA
edkrule-1.0.0.7.dist-info/WHEEL
edkrule-1.0.0.7.dist-info/top_level.txt
edkrule-1.0.0.7.dist-info/RECORD
